cdktf_cdktf_provider_ionoscloud/__init__.py
cdktf_cdktf_provider_ionoscloud/py.typed
cdktf_cdktf_provider_ionoscloud/_jsii/__init__.py
cdktf_cdktf_provider_ionoscloud/_jsii/provider-ionoscloud@12.0.12.jsii.tgz
cdktf_cdktf_provider_ionoscloud/apigateway/__init__.py
cdktf_cdktf_provider_ionoscloud/apigateway_route/__init__.py
cdktf_cdktf_provider_ionoscloud/application_loadbalancer/__init__.py
cdktf_cdktf_provider_ionoscloud/application_loadbalancer_forwardingrule/__init__.py
cdktf_cdktf_provider_ionoscloud/auto_certificate/__init__.py
cdktf_cdktf_provider_ionoscloud/auto_certificate_provider/__init__.py
cdktf_cdktf_provider_ionoscloud/autoscaling_group/__init__.py
cdktf_cdktf_provider_ionoscloud/backup_unit/__init__.py
cdktf_cdktf_provider_ionoscloud/cdn_distribution/__init__.py
cdktf_cdktf_provider_ionoscloud/certificate/__init__.py
cdktf_cdktf_provider_ionoscloud/container_registry/__init__.py
cdktf_cdktf_provider_ionoscloud/container_registry_token/__init__.py
cdktf_cdktf_provider_ionoscloud/cube_server/__init__.py
cdktf_cdktf_provider_ionoscloud/data_ionoscloud_apigateway/__init__.py
cdktf_cdktf_provider_ionoscloud/data_ionoscloud_apigateway_route/__init__.py
cdktf_cdktf_provider_ionoscloud/data_ionoscloud_application_loadbalancer/__init__.py
cdktf_cdktf_provider_ionoscloud/data_ionoscloud_application_loadbalancer_forwardingrule/__init__.py
cdktf_cdktf_provider_ionoscloud/data_ionoscloud_auto_certificate/__init__.py
cdktf_cdktf_provider_ionoscloud/data_ionoscloud_auto_certificate_provider/__init__.py
cdktf_cdktf_provider_ionoscloud/data_ionoscloud_autoscaling_group/__init__.py
cdktf_cdktf_provider_ionoscloud/data_ionoscloud_autoscaling_group_servers/__init__.py
cdktf_cdktf_provider_ionoscloud/data_ionoscloud_backup_unit/__init__.py
cdktf_cdktf_provider_ionoscloud/data_ionoscloud_cdn_distribution/__init__.py
cdktf_cdktf_provider_ionoscloud/data_ionoscloud_certificate/__init__.py
cdktf_cdktf_provider_ionoscloud/data_ionoscloud_container_registry/__init__.py
cdktf_cdktf_provider_ionoscloud-12.0.12.dist-info/LICENSE
cdktf_cdktf_provider_ionoscloud-12.0.12.dist-info/METADATA
cdktf_cdktf_provider_ionoscloud-12.0.12.dist-info/WHEEL
cdktf_cdktf_provider_ionoscloud-12.0.12.dist-info/top_level.txt
cdktf_cdktf_provider_ionoscloud-12.0.12.dist-info/RECORD
